pdf_info/__init__.py
pdf_info-2.1.0.dist-info/License.txt
pdf_info-2.1.0.dist-info/METADATA
pdf_info-2.1.0.dist-info/WHEEL
pdf_info-2.1.0.dist-info/top_level.txt
pdf_info-2.1.0.dist-info/RECORD
