Metadata-Version: 2.1
Name: pdf-info
Version: 2.1.0
Summary: This package extracts important information from a pdf document such as heading, paragraphs and important keywords!!!
Home-page: UNKNOWN
Author: Satyam Prakash
License: UNKNOWN
Platform: UNKNOWN
Requires-Dist: PymuPdf
Requires-Dist: nltk
Requires-Dist: pdfminer
Requires-Dist: sklearn
Requires-Dist: numpy
Requires-Dist: PyPDF2
